pysleep-0.1.6.dist-info/METADATA
pysleep-0.1.6.dist-info/WHEEL
pysleep-0.1.6.dist-info/entry_points.txt
pysleep-0.1.6.dist-info/licenses/LICENSE
pysleep/__init__.py
pysleep/hypnogram_report.py
pysleep/label.py
pysleep/stat.py
pysleep/stat_test.py
pysleep-0.1.6.dist-info/RECORD
